AUTHORS.rst
CONTRIBUTING.rst
HISTORY.rst
LICENSE
MANIFEST.in
README.rst
setup.cfg
setup.py
docs/Makefile
docs/authors.rst
docs/conf.py
docs/contributing.rst
docs/history.rst
docs/index.rst
docs/installation.rst
docs/make.bat
docs/readme.rst
docs/usage.rst
mremote/__init__.py
mremote/mremote.py
mremote.egg-info/PKG-INFO
mremote.egg-info/SOURCES.txt
mremote.egg-info/dependency_links.txt
mremote.egg-info/entry_points.txt
mremote.egg-info/not-zip-safe
mremote.egg-info/requires.txt
mremote.egg-info/top_level.txt
mremote/static/dot.js
mremote/templates/index.html
tests/__init__.py
tests/test_magic_lightning_remote.py