Metadata-Version: 1.1
Name: mremote
Version: 0.1.7
Summary: Generic LIRC web controller
Home-page: https://github.com/XayOn/mremote
Author: David Francos Cuartero
Author-email: me@davidfrancos.net
License: BSD
Keywords: mremote
Platform: UNKNOWN
Classifier: Development Status :: 2 - Pre-Alpha
Classifier: Intended Audience :: Developers
Classifier: License :: OSI Approved :: BSD License
Classifier: Natural Language :: English
Classifier: Programming Language :: Python :: 2
Classifier: Programming Language :: Python :: 2.6
Classifier: Programming Language :: Python :: 2.7
Classifier: Programming Language :: Python :: 3
Classifier: Programming Language :: Python :: 3.3
Classifier: Programming Language :: Python :: 3.4
